MANIFEST.in
README.rst
TODO
UPGRADE
setup.py
examplesite/__init__.py
examplesite/dispatcher.fcgi
examplesite/export_settings.py
examplesite/kiwi_doc.json
examplesite/manage.py
examplesite/settings.py
examplesite/urls.py
examplesite/kiwi/__init__.py
examplesite/kiwi/admin.py
examplesite/kiwi/dump.py
examplesite/kiwi/exporter.py
examplesite/kiwi/managers.py
examplesite/kiwi/models.py
examplesite/kiwi/tests.py
examplesite/kiwi/urls.py
examplesite/kiwi/fixtures/initial_data.json
examplesite/kiwi/static/kiwi/css/admin.css
examplesite/kiwi/static/kiwi/css/wiki.css
examplesite/kiwi/static/kiwi/css/images/child.gif
examplesite/kiwi/static/kiwi/css/images/parent.gif
examplesite/kiwi/static/kiwi/flash/mediaplayer/player.swf
examplesite/kiwi/static/kiwi/flash/mediaplayer/preview.jpg
examplesite/kiwi/static/kiwi/flash/mediaplayer/readme.html
examplesite/kiwi/static/kiwi/flash/mediaplayer/swfobject.js
examplesite/kiwi/static/kiwi/flash/mediaplayer/video.flv
examplesite/kiwi/static/kiwi/flash/mediaplayer/yt.swf
examplesite/kiwi/static/kiwi/js/admin.js
examplesite/kiwi/static/kiwi/js/bof_editor/README
examplesite/kiwi/static/kiwi/js/bof_editor/api.js
examplesite/kiwi/static/kiwi/js/bof_editor/fake_preview.html
examplesite/kiwi/static/kiwi/js/bof_editor/test_accept_events.html
examplesite/kiwi/static/kiwi/js/bof_editor/test_default.html
examplesite/kiwi/static/kiwi/js/bof_editor/test_full.html
examplesite/kiwi/static/kiwi/js/bof_editor/test_set.html
examplesite/kiwi/static/kiwi/js/bof_editor/test_wikibar.html
examplesite/kiwi/static/kiwi/js/bof_editor/ui.css
examplesite/kiwi/static/kiwi/js/bof_editor/images/remove.png
examplesite/kiwi/static/kiwi/js/bof_editor/images/remove_on.png
examplesite/kiwi/static/kiwi/js/bof_editor/wikibar/README
examplesite/kiwi/static/kiwi/js/bof_editor/wikibar/api.js
examplesite/kiwi/static/kiwi/js/bof_editor/wikibar/fake_help.html
examplesite/kiwi/static/kiwi/js/bof_editor/wikibar/test.html
kiwi_project.egg-info/PKG-INFO
kiwi_project.egg-info/SOURCES.txt
kiwi_project.egg-info/dependency_links.txt
kiwi_project.egg-info/not-zip-safe
kiwi_project.egg-info/requires.txt
kiwi_project.egg-info/top_level.txt