Metadata-Version: 1.0
Name: kiwi-project
Version: 1.3.9.1
Summary: Kiwi est un module Django dont le but est de gérer des pages Wiki
Home-page: UNKNOWN
Author: Thenon David
Author-email: sveetch AT gmail.com
License: GNU General Public License
Platform: UNKNOWN
Classifier: Programming Language :: Python
Classifier: License :: OSI Approved :: MIT License
Classifier: Operating System :: OS Independent
Classifier: Development Status :: 7 - Inactive
Classifier: Environment :: Web Environment
Classifier: Intended Audience :: Developers
Classifier: Topic :: Internet :: WWW/HTTP
Classifier: Topic :: Software Development :: Libraries :: Python Modules
